Metadata-Version: 1.0
Name: jjyyzz-distributions
Version: 1.0
Summary: Gaussian and Binomial distributions
Home-page: UNKNOWN
Author: Jiuyue Zhou
Author-email: UNKNOWN
License: UNKNOWN
Platform: UNKNOWN
